datasette_query_assistant/__init__.py
datasette_query_assistant/templates/query_assistant.html
datasette_query_assistant-0.1a5.dist-info/licenses/LICENSE
datasette_query_assistant-0.1a5.dist-info/METADATA
datasette_query_assistant-0.1a5.dist-info/WHEEL
datasette_query_assistant-0.1a5.dist-info/entry_points.txt
datasette_query_assistant-0.1a5.dist-info/top_level.txt
datasette_query_assistant-0.1a5.dist-info/RECORD
