Metadata-Version: 2.4
Name: datasette-query-assistant
Version: 0.1a5
Summary: Query databases and tables with AI assistance
Author: Simon Willison
License-Expression: Apache-2.0
Project-URL: Homepage, https://github.com/datasette/datasette-query-assistant
Project-URL: Changelog, https://github.com/datasette/datasette-query-assistant/releases
Project-URL: Issues, https://github.com/datasette/datasette-query-assistant/issues
Project-URL: CI, https://github.com/datasette/datasette-query-assistant/actions
Classifier: Framework :: Datasette
Requires-Python: >=3.10
License-File: LICENSE
Requires-Dist: datasette>=1.0a21
Requires-Dist: llm>=0.22
Requires-Dist: markdown2
Provides-Extra: test
Requires-Dist: llm-openai-plugin; extra == "test"
Requires-Dist: inline-snapshot; extra == "test"
Requires-Dist: pytest; extra == "test"
Requires-Dist: pytest-asyncio; extra == "test"
Requires-Dist: pytest-recording; extra == "test"
Requires-Dist: sqlite-utils; extra == "test"
Dynamic: license-file
